rockpaperscissor_domroon/__init__.py
rockpaperscissor_domroon/app.py
rockpaperscissor_domroon-0.1.0.dist-info/LICENSE.rst
rockpaperscissor_domroon-0.1.0.dist-info/WHEEL
rockpaperscissor_domroon-0.1.0.dist-info/METADATA
rockpaperscissor_domroon-0.1.0.dist-info/RECORD
